<annotation>
	<folder>Ikan Bawal</folder>
	<filename>Ikan Bawal (39).jpg</filename>
	<path>C:\Users\Forge-15\Desktop\Fish Species Datasets\Ikan Bawal\Ikan Bawal (39).jpg</path>
	<source>
		<database>Unknown</database>
	</source>
	<size>
		<width>480</width>
		<height>360</height>
		<depth>3</depth>
	</size>
	<segmented>0</segmented>
	<object>
		<name>Ikan Bawal</name>
		<pose>Unspecified</pose>
		<truncated>0</truncated>
		<difficult>0</difficult>
		<bndbox>
			<xmin>16</xmin>
			<ymin>66</ymin>
			<xmax>463</xmax>
			<ymax>311</ymax>
		</bndbox>
	</object>
</annotation>
